casearch/__init__.py
casearch/cli.py
casearch/config.py
casearch/log.py
casearch/retrieve.py
casearch-0.2.7.dist-info/LICENSE
casearch-0.2.7.dist-info/METADATA
casearch-0.2.7.dist-info/WHEEL
casearch-0.2.7.dist-info/entry_points.txt
casearch-0.2.7.dist-info/top_level.txt
casearch-0.2.7.dist-info/RECORD
