Metadata-Version: 2.1
Name: casearch
Version: 0.2.7
Summary: Retrieve cases from ElasticSearch
Home-page: https://github.com/EathonTnT/casearch
Author: TnTomato
Author-email: 474093103@qq.com
License: MIT
Platform: UNKNOWN
Requires-Python: >=3.6
Requires-Dist: elasticsearch (>=6.3.0)
Requires-Dist: elasticsearch-dsl (>=6.3.0)
Requires-Dist: click (>=7.0)
Requires-Dist: pymongo (>=3.6.0)
Requires-Dist: python-dotenv (>=0.10.0)
